{
  "comentario": "Mapeamento de clubes para logos locais. Gerado automaticamente.",
  "estrutura": "clubes: { [club_id]: \"caminho/relativo/logo.png\" }, clubesPorNome: { [nome_slug]: \"caminho/relativo/logo.png\" }, clubesPorLigaNome: { [liga_id]: { [nome_slug]: \"caminho/relativo/logo.png\" } }",
  "timestamp": "2026-06-26T14:16:32.998Z",
  "clubes": {
    "19": "./Ligas/Liga Brasil/brazil_vasco-da-gama_512x512.football-logos.cc.png",
    "20": "./Ligas/Liga Brasil/brazil_vitoria_512x512.football-logos.cc.png",
    "1011": "./Ligas/Liga Argentina/argentina_boca-juniors_512x512.football-logos.cc.png",
    "1012": "./Ligas/Liga Argentina/argentina_river-plate_512x512.football-logos.cc.png",
    "1013": "./Ligas/Liga Argentina/argentina_racing-club_512x512.football-logos.cc.png",
    "1014": "./Ligas/Liga Argentina/argentina_independiente_512x512.football-logos.cc.png",
    "1015": "./Ligas/Liga Argentina/argentina_estudiantes-de-rio-cuarto_512x512.football-logos.cc.png",
    "1021": "./Ligas/Liga Mexico/mexico_club-america_512x512.football-logos.cc.png",
    "1022": "./Ligas/Liga Mexico/mexico_atlas_512x512.football-logos.cc.png",
    "1023": "./Ligas/Liga Mexico/mexico_atletico-de-san-luis_512x512.football-logos.cc.png",
    "1024": "./Ligas/Liga Mexico/mexico_cruz-azul_512x512.football-logos.cc.png",
    "1025": "./Ligas/Liga Mexico/mexico_cd-guadalajara_512x512.football-logos.cc.png",
    "1026": "./Ligas/Liga Mexico/mexico_fc-juarez_512x512.football-logos.cc.png",
    "1027": "./Ligas/Liga Mexico/mexico_club-leon_512x512.football-logos.cc.png",
    "1028": "./Ligas/Liga Mexico/mexico_monterrey_512x512.football-logos.cc.png",
    "1029": "./Ligas/Liga Mexico/mexico_necaxa_512x512.football-logos.cc.png",
    "1030": "./Ligas/Liga Mexico/mexico_pachuca_512x512.football-logos.cc.png",
    "1036": "./Ligas/Liga Mexico/mexico_tigres-uanl_512x512.football-logos.cc.png",
    "1037": "./Ligas/Liga Mexico/mexico_unam-pumas_512x512.football-logos.cc.png",
    "1038": "./Ligas/Liga Mexico/mexico_mazatlan-fc_512x512.football-logos.cc.png",
    "1041": "./Ligas/Liga Alemanha/germany_bayern-munchen_512x512.football-logos.cc.png",
    "1042": "./Ligas/Liga Alemanha/germany_borussia-dortmund_512x512.football-logos.cc.png",
    "1043": "./Ligas/Liga Alemanha/germany_rb-leipzig_512x512.football-logos.cc.png",
    "1044": "./Ligas/Liga Alemanha/germany_bayer-leverkusen_512x512.football-logos.cc.png",
    "1051": "./Ligas/Liga USA/usa_la-galaxy_512x512.football-logos.cc.png",
    "1052": "./Ligas/Liga USA/usa_inter-miami-cf_512x512.football-logos.cc.png",
    "1053": "./Ligas/Liga USA/usa_atlanta-united_512x512.football-logos.cc.png",
    "1054": "./Ligas/Liga USA/usa_seattle-sounders-fc_512x512.football-logos.cc.png",
    "1055": "./Ligas/Liga USA/usa_new-york-city-fc_512x512.football-logos.cc.png",
    "1061": "./Ligas/Liga Japão/japan_urawa-reds_512x512.football-logos.cc.png",
    "1062": "./Ligas/Liga Japão/japan_kashima-antlers_512x512.football-logos.cc.png",
    "1063": "./Ligas/Liga Japão/japan_yokohama-f-marinos_512x512.football-logos.cc.png",
    "1064": "./Ligas/Liga Japão/japan_shimizu-s-pulse_512x512.football-logos.cc.png",
    "1065": "./Ligas/Liga Japão/japan_gamba-osaka_512x512.football-logos.cc.png",
    "1071": "./Ligas/Liga Korea/south-korea_jeonbuk_512x512.football-logos.cc.png",
    "1072": "./Ligas/Liga Korea/south-korea_ulsan-hd-fc_512x512.football-logos.cc.png",
    "1073": "./Ligas/Liga Korea/south-korea_fc-seoul_512x512.football-logos.cc.png",
    "1074": "./Ligas/Liga Korea/south-korea_pohang-steelers_512x512.football-logos.cc.png",
    "1075": "./Ligas/Liga Korea/south-korea_suwon-fc_512x512.football-logos.cc.png",
    "1081": "./Ligas/Liga Indonésia/indonesia_persija-jakarta_512x512.football-logos.cc.png",
    "1083": "./Ligas/Liga Indonésia/indonesia_arema-fc_512x512.football-logos.cc.png",
    "1084": "./Ligas/Liga Indonésia/indonesia_persib-bandung_512x512.football-logos.cc.png",
    "1085": "./Ligas/Liga Indonésia/indonesia_psm-makassar_512x512.football-logos.cc.png",
    "1091": "./Ligas/Liga Filandia/finland_hjk_512x512.football-logos.cc.png",
    "1092": "./Ligas/Liga Filandia/finland_kups_512x512.football-logos.cc.png",
    "1093": "./Ligas/Liga Filandia/finland_inter-turku_512x512.football-logos.cc.png",
    "1094": "./Ligas/Liga Filandia/finland_ilves_512x512.football-logos.cc.png"
  },
  "clubesPorNome": {
    "bayer-leverkusen": "./Ligas/Liga Alemanha/germany_bayer-leverkusen_512x512.football-logos.cc.png",
    "bayern-munique": "./Ligas/Liga Alemanha/germany_bayern-munchen_512x512.football-logos.cc.png",
    "borussia-dortmund": "./Ligas/Liga Alemanha/germany_borussia-dortmund_512x512.football-logos.cc.png",
    "rb-leipzig": "./Ligas/Liga Alemanha/germany_rb-leipzig_512x512.football-logos.cc.png",
    "boca-juniors": "./Ligas/Liga Argentina/argentina_boca-juniors_512x512.football-logos.cc.png",
    "estudiantes": "./Ligas/Liga Argentina/argentina_estudiantes-de-la-plata_512x512.football-logos.cc.png",
    "independiente": "./Ligas/Liga Argentina/argentina_independiente-rivadavia_512x512.football-logos.cc.png",
    "racing-club": "./Ligas/Liga Argentina/argentina_racing-club_512x512.football-logos.cc.png",
    "river-plate": "./Ligas/Liga Argentina/argentina_river-plate_512x512.football-logos.cc.png",
    "atletico-mineiro": "./Ligas/Liga Brasil/brazil_atletico-mineiro_512x512.football-logos.cc.png",
    "bahia": "./Ligas/Liga Brasil/brazil_bahia_512x512.football-logos.cc.png",
    "botafogo": "./Ligas/Liga Brasil/brazil_botafogo_512x512.football-logos.cc.png",
    "corinthians": "./Ligas/Liga Brasil/brazil_corinthians_512x512.football-logos.cc.png",
    "cruzeiro": "./Ligas/Liga Brasil/brazil_cruzeiro_512x512.football-logos.cc.png",
    "flamengo": "./Ligas/Liga Brasil/brazil_flamengo_512x512.football-logos.cc.png",
    "fluminense": "./Ligas/Liga Brasil/brazil_fluminense_512x512.football-logos.cc.png",
    "gremio": "./Ligas/Liga Brasil/brazil_gremio_512x512.football-logos.cc.png",
    "internacional": "./Ligas/Liga Brasil/brazil_internacional_512x512.football-logos.cc.png",
    "mirassol": "./Ligas/Liga Brasil/brazil_mirassol_512x512.football-logos.cc.png",
    "palmeiras": "./Ligas/Liga Brasil/brazil_palmeiras_512x512.football-logos.cc.png",
    "santos": "./Ligas/Liga Brasil/brazil_santos_512x512.football-logos.cc.png",
    "sao-paulo": "./Ligas/Liga Brasil/brazil_sao-paulo_512x512.football-logos.cc.png",
    "vasco-da-gama": "./Ligas/Liga Brasil/brazil_vasco-da-gama_512x512.football-logos.cc.png",
    "vitoria": "./Ligas/Liga Brasil/brazil_vitoria_512x512.football-logos.cc.png",
    "hjk-helsinki": "./Ligas/Liga Filandia/finland_hjk_512x512.football-logos.cc.png",
    "ilves": "./Ligas/Liga Filandia/finland_ilves_512x512.football-logos.cc.png",
    "fc-inter-turku": "./Ligas/Liga Filandia/finland_inter-turku_512x512.football-logos.cc.png",
    "kups": "./Ligas/Liga Filandia/finland_kups_512x512.football-logos.cc.png",
    "as-monaco": "./Ligas/Liga França/france_as-monaco_512x512.football-logos.cc.png",
    "losc-lille": "./Ligas/Liga França/france_lille_512x512.football-logos.cc.png",
    "olympique-lyon": "./Ligas/Liga França/france_lyon_512x512.football-logos.cc.png",
    "olympique-marseille": "./Ligas/Liga França/france_marseille_512x512.football-logos.cc.png",
    "paris-saint-germain": "./Ligas/Liga França/france_paris-saint-germain_512x512.football-logos.cc.png",
    "arema-fc": "./Ligas/Liga Indonésia/indonesia_arema-fc_512x512.football-logos.cc.png",
    "persib-bandung": "./Ligas/Liga Indonésia/indonesia_persib-bandung_512x512.football-logos.cc.png",
    "persija-jakarta": "./Ligas/Liga Indonésia/indonesia_persija-jakarta_512x512.football-logos.cc.png",
    "psm-makassar": "./Ligas/Liga Indonésia/indonesia_psm-makassar_512x512.football-logos.cc.png",
    "gamba-osaka": "./Ligas/Liga Japão/japan_gamba-osaka_512x512.football-logos.cc.png",
    "kashima-antlers": "./Ligas/Liga Japão/japan_kashima-antlers_512x512.football-logos.cc.png",
    "shimizu-s-pulse": "./Ligas/Liga Japão/japan_shimizu-s-pulse_512x512.football-logos.cc.png",
    "urawa-red-diamonds": "./Ligas/Liga Japão/japan_urawa-reds_512x512.football-logos.cc.png",
    "yokohama-f-marinos": "./Ligas/Liga Japão/japan_yokohama-f-marinos_512x512.football-logos.cc.png",
    "fc-seoul": "./Ligas/Liga Korea/south-korea_fc-seoul_512x512.football-logos.cc.png",
    "jeonbuk-hyundai-motors": "./Ligas/Liga Korea/south-korea_jeonbuk_512x512.football-logos.cc.png",
    "pohang-steelers": "./Ligas/Liga Korea/south-korea_pohang-steelers_512x512.football-logos.cc.png",
    "suwon-samsung-bluewings": "./Ligas/Liga Korea/south-korea_suwon-fc_512x512.football-logos.cc.png",
    "ulsan-hyundai": "./Ligas/Liga Korea/south-korea_ulsan-hd-fc_512x512.football-logos.cc.png",
    "atlas-fc": "./Ligas/Liga Mexico/mexico_atlas_512x512.football-logos.cc.png",
    "atletico-san-luis": "./Ligas/Liga Mexico/mexico_atletico-de-san-luis_512x512.football-logos.cc.png",
    "club-deportivo-guadalajara": "./Ligas/Liga Mexico/mexico_cd-guadalajara_512x512.football-logos.cc.png",
    "club-america": "./Ligas/Liga Mexico/mexico_club-america_512x512.football-logos.cc.png",
    "club-leon": "./Ligas/Liga Mexico/mexico_club-leon_512x512.football-logos.cc.png",
    "club-tijuana": "./Ligas/Liga Mexico/mexico_club-tijuana_512x512.football-logos.cc.png",
    "cruz-azul": "./Ligas/Liga Mexico/mexico_cruz-azul_512x512.football-logos.cc.png",
    "fc-juarez": "./Ligas/Liga Mexico/mexico_fc-juarez_512x512.football-logos.cc.png",
    "mazatlan-fc": "./Ligas/Liga Mexico/mexico_mazatlan-fc_512x512.football-logos.cc.png",
    "cf-monterrey": "./Ligas/Liga Mexico/mexico_monterrey_512x512.football-logos.cc.png",
    "necaxa": "./Ligas/Liga Mexico/mexico_necaxa_512x512.football-logos.cc.png",
    "pachuca": "./Ligas/Liga Mexico/mexico_pachuca_512x512.football-logos.cc.png",
    "puebla-fc": "./Ligas/Liga Mexico/mexico_puebla_512x512.football-logos.cc.png",
    "queretaro-fc": "./Ligas/Liga Mexico/mexico_queretaro-fc_512x512.football-logos.cc.png",
    "santos-laguna": "./Ligas/Liga Mexico/mexico_santos-laguna_512x512.football-logos.cc.png",
    "tigres-uanl": "./Ligas/Liga Mexico/mexico_tigres-uanl_512x512.football-logos.cc.png",
    "toluca": "./Ligas/Liga Mexico/mexico_toluca_512x512.football-logos.cc.png",
    "pumas-unam": "./Ligas/Liga Mexico/mexico_unam-pumas_512x512.football-logos.cc.png",
    "arouca": "./Ligas/Liga Portugal/portugal_arouca_512x512.football-logos.cc.png",
    "avs": "./Ligas/Liga Portugal/portugal_avs-futebol-sad_512x512.football-logos.cc.png",
    "sl-benfica": "./Ligas/Liga Portugal/portugal_benfica_512x512.football-logos.cc.png",
    "casa-pia-ac": "./Ligas/Liga Portugal/portugal_casa-pia-ac_512x512.football-logos.cc.png",
    "estoril-praia": "./Ligas/Liga Portugal/portugal_estoril_512x512.football-logos.cc.png",
    "estrela-da-amadora": "./Ligas/Liga Portugal/portugal_estrela-da-amadora_512x512.football-logos.cc.png",
    "fc-famalicao": "./Ligas/Liga Portugal/portugal_famalicao_512x512.football-logos.cc.png",
    "fc-porto": "./Ligas/Liga Portugal/portugal_fc-porto_512x512.football-logos.cc.png",
    "gil-vicente-fc": "./Ligas/Liga Portugal/portugal_gil-vicente_512x512.football-logos.cc.png",
    "moreirense-fc": "./Ligas/Liga Portugal/portugal_moreirense_512x512.football-logos.cc.png",
    "cd-nacional": "./Ligas/Liga Portugal/portugal_nacional-da-madeira_512x512.football-logos.cc.png",
    "rio-ave-fc": "./Ligas/Liga Portugal/portugal_rio-ave_512x512.football-logos.cc.png",
    "santa-clara": "./Ligas/Liga Portugal/portugal_santa-clara_512x512.football-logos.cc.png",
    "sc-braga": "./Ligas/Liga Portugal/portugal_sc-braga_512x512.football-logos.cc.png",
    "sporting-cp": "./Ligas/Liga Portugal/portugal_sporting-cp_512x512.football-logos.cc.png",
    "tondela": "./Ligas/Liga Portugal/portugal_tondela_512x512.football-logos.cc.png",
    "vitoria-sc": "./Ligas/Liga Portugal/portugal_vitoria-de-guimaraes_512x512.football-logos.cc.png",
    "atlanta-united": "./Ligas/Liga USA/usa_atlanta-united_512x512.football-logos.cc.png",
    "inter-miami-cf": "./Ligas/Liga USA/usa_inter-miami-cf_512x512.football-logos.cc.png",
    "la-galaxy": "./Ligas/Liga USA/usa_la-galaxy_512x512.football-logos.cc.png",
    "new-york-city-fc": "./Ligas/Liga USA/usa_new-york-city-fc_512x512.football-logos.cc.png",
    "seattle-sounders": "./Ligas/Liga USA/usa_seattle-sounders-fc_512x512.football-logos.cc.png"
  },
  "clubesPorLigaNome": {
    "7:bayer-leverkusen": "./Ligas/Liga Alemanha/germany_bayer-leverkusen_512x512.football-logos.cc.png",
    "7:bayern-munique": "./Ligas/Liga Alemanha/germany_bayern-munchen_512x512.football-logos.cc.png",
    "7:borussia-dortmund": "./Ligas/Liga Alemanha/germany_borussia-dortmund_512x512.football-logos.cc.png",
    "7:rb-leipzig": "./Ligas/Liga Alemanha/germany_rb-leipzig_512x512.football-logos.cc.png",
    "3:boca-juniors": "./Ligas/Liga Argentina/argentina_boca-juniors_512x512.football-logos.cc.png",
    "3:estudiantes": "./Ligas/Liga Argentina/argentina_estudiantes-de-rio-cuarto_512x512.football-logos.cc.png",
    "3:independiente": "./Ligas/Liga Argentina/argentina_independiente_512x512.football-logos.cc.png",
    "3:racing-club": "./Ligas/Liga Argentina/argentina_racing-club_512x512.football-logos.cc.png",
    "3:river-plate": "./Ligas/Liga Argentina/argentina_river-plate_512x512.football-logos.cc.png",
    "2:atletico-mineiro": "./Ligas/Liga Brasil/brazil_atletico-mineiro_512x512.football-logos.cc.png",
    "2:bahia": "./Ligas/Liga Brasil/brazil_bahia_512x512.football-logos.cc.png",
    "2:botafogo": "./Ligas/Liga Brasil/brazil_botafogo_512x512.football-logos.cc.png",
    "2:corinthians": "./Ligas/Liga Brasil/brazil_corinthians_512x512.football-logos.cc.png",
    "2:cruzeiro": "./Ligas/Liga Brasil/brazil_cruzeiro_512x512.football-logos.cc.png",
    "2:flamengo": "./Ligas/Liga Brasil/brazil_flamengo_512x512.football-logos.cc.png",
    "2:fluminense": "./Ligas/Liga Brasil/brazil_fluminense_512x512.football-logos.cc.png",
    "2:gremio": "./Ligas/Liga Brasil/brazil_gremio_512x512.football-logos.cc.png",
    "2:internacional": "./Ligas/Liga Brasil/brazil_internacional_512x512.football-logos.cc.png",
    "2:mirassol": "./Ligas/Liga Brasil/brazil_mirassol_512x512.football-logos.cc.png",
    "2:palmeiras": "./Ligas/Liga Brasil/brazil_palmeiras_512x512.football-logos.cc.png",
    "2:santos": "./Ligas/Liga Brasil/brazil_santos_512x512.football-logos.cc.png",
    "2:sao-paulo": "./Ligas/Liga Brasil/brazil_sao-paulo_512x512.football-logos.cc.png",
    "2:vasco-da-gama": "./Ligas/Liga Brasil/brazil_vasco-da-gama_512x512.football-logos.cc.png",
    "2:vitoria": "./Ligas/Liga Brasil/brazil_vitoria_512x512.football-logos.cc.png",
    "13:hjk-helsinki": "./Ligas/Liga Filandia/finland_hjk_512x512.football-logos.cc.png",
    "13:ilves": "./Ligas/Liga Filandia/finland_ilves_512x512.football-logos.cc.png",
    "13:fc-inter-turku": "./Ligas/Liga Filandia/finland_inter-turku_512x512.football-logos.cc.png",
    "13:kups": "./Ligas/Liga Filandia/finland_kups_512x512.football-logos.cc.png",
    "6:as-monaco": "./Ligas/Liga França/france_as-monaco_512x512.football-logos.cc.png",
    "6:losc-lille": "./Ligas/Liga França/france_lille_512x512.football-logos.cc.png",
    "6:olympique-lyon": "./Ligas/Liga França/france_lyon_512x512.football-logos.cc.png",
    "6:olympique-marseille": "./Ligas/Liga França/france_marseille_512x512.football-logos.cc.png",
    "6:paris-saint-germain": "./Ligas/Liga França/france_paris-saint-germain_512x512.football-logos.cc.png",
    "12:arema-fc": "./Ligas/Liga Indonésia/indonesia_arema-fc_512x512.football-logos.cc.png",
    "12:persib-bandung": "./Ligas/Liga Indonésia/indonesia_persib-bandung_512x512.football-logos.cc.png",
    "12:persija-jakarta": "./Ligas/Liga Indonésia/indonesia_persija-jakarta_512x512.football-logos.cc.png",
    "12:psm-makassar": "./Ligas/Liga Indonésia/indonesia_psm-makassar_512x512.football-logos.cc.png",
    "10:gamba-osaka": "./Ligas/Liga Japão/japan_gamba-osaka_512x512.football-logos.cc.png",
    "10:kashima-antlers": "./Ligas/Liga Japão/japan_kashima-antlers_512x512.football-logos.cc.png",
    "10:shimizu-s-pulse": "./Ligas/Liga Japão/japan_shimizu-s-pulse_512x512.football-logos.cc.png",
    "10:urawa-red-diamonds": "./Ligas/Liga Japão/japan_urawa-reds_512x512.football-logos.cc.png",
    "10:yokohama-f-marinos": "./Ligas/Liga Japão/japan_yokohama-f-marinos_512x512.football-logos.cc.png",
    "11:fc-seoul": "./Ligas/Liga Korea/south-korea_fc-seoul_512x512.football-logos.cc.png",
    "11:jeonbuk-hyundai-motors": "./Ligas/Liga Korea/south-korea_jeonbuk_512x512.football-logos.cc.png",
    "11:pohang-steelers": "./Ligas/Liga Korea/south-korea_pohang-steelers_512x512.football-logos.cc.png",
    "11:suwon-samsung-bluewings": "./Ligas/Liga Korea/south-korea_suwon-fc_512x512.football-logos.cc.png",
    "11:ulsan-hyundai": "./Ligas/Liga Korea/south-korea_ulsan-hd-fc_512x512.football-logos.cc.png",
    "4:atlas-fc": "./Ligas/Liga Mexico/mexico_atlas_512x512.football-logos.cc.png",
    "4:atletico-san-luis": "./Ligas/Liga Mexico/mexico_atletico-de-san-luis_512x512.football-logos.cc.png",
    "4:club-deportivo-guadalajara": "./Ligas/Liga Mexico/mexico_cd-guadalajara_512x512.football-logos.cc.png",
    "4:club-america": "./Ligas/Liga Mexico/mexico_club-america_512x512.football-logos.cc.png",
    "4:club-leon": "./Ligas/Liga Mexico/mexico_club-leon_512x512.football-logos.cc.png",
    "4:club-tijuana": "./Ligas/Liga Mexico/mexico_club-tijuana_512x512.football-logos.cc.png",
    "4:cruz-azul": "./Ligas/Liga Mexico/mexico_cruz-azul_512x512.football-logos.cc.png",
    "4:fc-juarez": "./Ligas/Liga Mexico/mexico_fc-juarez_512x512.football-logos.cc.png",
    "4:mazatlan-fc": "./Ligas/Liga Mexico/mexico_mazatlan-fc_512x512.football-logos.cc.png",
    "4:cf-monterrey": "./Ligas/Liga Mexico/mexico_monterrey_512x512.football-logos.cc.png",
    "4:necaxa": "./Ligas/Liga Mexico/mexico_necaxa_512x512.football-logos.cc.png",
    "4:pachuca": "./Ligas/Liga Mexico/mexico_pachuca_512x512.football-logos.cc.png",
    "4:puebla-fc": "./Ligas/Liga Mexico/mexico_puebla_512x512.football-logos.cc.png",
    "4:queretaro-fc": "./Ligas/Liga Mexico/mexico_queretaro-fc_512x512.football-logos.cc.png",
    "4:santos-laguna": "./Ligas/Liga Mexico/mexico_santos-laguna_512x512.football-logos.cc.png",
    "4:tigres-uanl": "./Ligas/Liga Mexico/mexico_tigres-uanl_512x512.football-logos.cc.png",
    "4:toluca": "./Ligas/Liga Mexico/mexico_toluca_512x512.football-logos.cc.png",
    "4:pumas-unam": "./Ligas/Liga Mexico/mexico_unam-pumas_512x512.football-logos.cc.png",
    "1:arouca": "./Ligas/Liga Portugal/portugal_arouca_512x512.football-logos.cc.png",
    "1:avs": "./Ligas/Liga Portugal/portugal_avs-futebol-sad_512x512.football-logos.cc.png",
    "1:sl-benfica": "./Ligas/Liga Portugal/portugal_benfica_512x512.football-logos.cc.png",
    "1:casa-pia-ac": "./Ligas/Liga Portugal/portugal_casa-pia-ac_512x512.football-logos.cc.png",
    "1:estoril-praia": "./Ligas/Liga Portugal/portugal_estoril_512x512.football-logos.cc.png",
    "1:estrela-da-amadora": "./Ligas/Liga Portugal/portugal_estrela-da-amadora_512x512.football-logos.cc.png",
    "1:fc-famalicao": "./Ligas/Liga Portugal/portugal_famalicao_512x512.football-logos.cc.png",
    "1:fc-porto": "./Ligas/Liga Portugal/portugal_fc-porto_512x512.football-logos.cc.png",
    "1:gil-vicente-fc": "./Ligas/Liga Portugal/portugal_gil-vicente_512x512.football-logos.cc.png",
    "1:moreirense-fc": "./Ligas/Liga Portugal/portugal_moreirense_512x512.football-logos.cc.png",
    "1:cd-nacional": "./Ligas/Liga Portugal/portugal_nacional-da-madeira_512x512.football-logos.cc.png",
    "1:rio-ave-fc": "./Ligas/Liga Portugal/portugal_rio-ave_512x512.football-logos.cc.png",
    "1:santa-clara": "./Ligas/Liga Portugal/portugal_santa-clara_512x512.football-logos.cc.png",
    "1:sc-braga": "./Ligas/Liga Portugal/portugal_sc-braga_512x512.football-logos.cc.png",
    "1:sporting-cp": "./Ligas/Liga Portugal/portugal_sporting-cp_512x512.football-logos.cc.png",
    "1:tondela": "./Ligas/Liga Portugal/portugal_tondela_512x512.football-logos.cc.png",
    "1:vitoria-sc": "./Ligas/Liga Portugal/portugal_vitoria-de-guimaraes_512x512.football-logos.cc.png",
    "9:atlanta-united": "./Ligas/Liga USA/usa_atlanta-united_512x512.football-logos.cc.png",
    "9:inter-miami-cf": "./Ligas/Liga USA/usa_inter-miami-cf_512x512.football-logos.cc.png",
    "9:la-galaxy": "./Ligas/Liga USA/usa_la-galaxy_512x512.football-logos.cc.png",
    "9:new-york-city-fc": "./Ligas/Liga USA/usa_new-york-city-fc_512x512.football-logos.cc.png",
    "9:seattle-sounders": "./Ligas/Liga USA/usa_seattle-sounders-fc_512x512.football-logos.cc.png"
  }
}